wmata/__init__.py
wmata/date.py
wmata/error.py
wmata/location.py
wmata/mixins.py
wmata/responses.py
wmata/utils.py
wmata/bus/__init__.py
wmata/bus/client.py
wmata/bus/mixins.py
wmata/bus/responses.py
wmata/bus/route.py
wmata/bus/stop.py
wmata/bus/urls.py
wmata/bus/tests/__init__.py
wmata/bus/tests/test_client.py
wmata/bus/tests/test_mixins.py
wmata/bus/tests/test_responses.py
wmata/bus/tests/utils.py
wmata/rail/__init__.py
wmata/rail/client.py
wmata/rail/line.py
wmata/rail/mixins.py
wmata/rail/responses.py
wmata/rail/station.py
wmata/rail/urls.py
wmata/rail/tests/__init__.py
wmata/rail/tests/test_client.py
wmata/rail/tests/test_mixins.py
wmata/rail/tests/test_responses.py
wmata/rail/tests/utils.py
wmata-1.0.0.dist-info/LICENSE
wmata-1.0.0.dist-info/METADATA
wmata-1.0.0.dist-info/WHEEL
wmata-1.0.0.dist-info/top_level.txt
wmata-1.0.0.dist-info/RECORD
