Metadata-Version: 2.1
Name: wmata
Version: 1.0.0
Summary: A simple interface to the WMATA API
Home-page: https://github.com/emma-k-alexandra/pywmata
Author: Emma K Alexandra
Author-email: emma@emma.sh
License: UNKNOWN
Platform: UNKNOWN
Classifier: Programming Language :: Python :: 3
Classifier: License :: OSI Approved :: MIT License
Classifier: Operating System :: OS Independent
Requires-Python: >=3.8
Requires-Dist: requests2
